hocon_validator/__init__.py
hocon_validator/hocon_validator.py
hocon_validator-0.1.1.dist-info/DESCRIPTION.rst
hocon_validator-0.1.1.dist-info/METADATA
hocon_validator-0.1.1.dist-info/RECORD
hocon_validator-0.1.1.dist-info/WHEEL
hocon_validator-0.1.1.dist-info/entry_points.txt
hocon_validator-0.1.1.dist-info/metadata.json
hocon_validator-0.1.1.dist-info/top_level.txt
