Metadata-Version: 2.0
Name: hocon-validator
Version: 0.1.1
Summary: A HOCON validator
Home-page: UNKNOWN
Author: Aki Ariga chezou
Author-email: chezou@gmail.com
License: Apache License 2.0
Keywords: HOCON validator
Platform: UNKNOWN
Classifier: Development Status :: 3 - Alpha
Classifier: Intended Audience :: Developers
Classifier: License :: OSI Approved :: Apache Software License
Classifier: Programming Language :: Python :: 2
Classifier: Programming Language :: Python :: 2.7
Classifier: Programming Language :: Python :: 3
Classifier: Programming Language :: Python :: 3.6
Requires-Dist: pyhocon
Requires-Dist: pyyaml
